{
  "posts": [
    {
      "title": "Почитать",
      "id": 1,
      "description": [
        {
          "id": 1,
          "checkbox": true,
          "text": "Человек который принял свою жену за шляпу"
        },
        {
          "id": 2,
          "checkbox": false,
          "text": "Антрополог на Марсе"
        },
        {
          "id": 3,
          "checkbox": false,
          "text": "Крысиный остров"
        }
      ]
    },
    {
      "title": "Купить для флорариума",
      "id": 2,
      "description": [
        {
          "id": 1,
          "checkbox": false,
          "text": "Стекло"
        },
        {
          "id": 2,
          "checkbox": false,
          "text": "ПОС 61"
        },
        {
          "id": 3,
          "checkbox": false,
          "text": "Припой"
        },
        {
          "id": 4,
          "checkbox": false,
          "text": "Медная лента"
        },
        {
          "id": 5,
          "checkbox": false,
          "text": "Патина"
        }
      ]
    },
    {
      "title": "Добавить функционал в приложении",
      "id": 3,
      "description": [
        {
          "id": 1,
          "checkbox": false,
          "text": "Возможность создавать открытые/закрытые мероприятия"
        },
        {
          "id": 2,
          "checkbox": false,
          "text": "Добавление в друзья"
        },
        {
          "id": 3,
          "checkbox": false,
          "text": "Смена города"
        },
        {
          "id": 4,
          "checkbox": false,
          "text": "Оповещение о наступлении события на которое подписан"
        }
      ]
    }
  ]
}